khmernlp/__init__.py
khmernlp/tokenizer/__init__.py
khmernlp/tokenizer/network.py
khmernlp/tokenizer/tokenizer.py
khmernlp/tokenizer/configs/original_paper.json
khmernlp/tokenizer/pretrained/char_map.txt
khmernlp/tokenizer/pretrained/original_paper.json
khmernlp/tokenizer/pretrained/original_paper.tflite
khmernlp/tokenizer/pretrained/original_paper.weights.h5
khmernlp/tokenizer/pretrained/pos_map.txt
khmernlp/tokenizer/utils/__init__.py
khmernlp/tokenizer/utils/create_mapping.py
khmernlp/tokenizer/utils/prepare_khpos_dataset.py
khmernlp/tokenizer/utils/read_char_map.py
khmernlp/tokenizer/utils/read_config.py
khmernlp/tokenizer/utils/read_pos_map.py
khmernlp/tokenizer/utils/read_samples.py
khmernlp/tokenizer/utils/str2bool.py
khmernlp-0.0.1.dist-info/LICENSE
khmernlp-0.0.1.dist-info/METADATA
khmernlp-0.0.1.dist-info/WHEEL
khmernlp-0.0.1.dist-info/top_level.txt
khmernlp-0.0.1.dist-info/RECORD
