Metadata-Version: 2.1
Name: khmernlp
Version: 0.0.1
Summary: Khmer NLP is a package for running natural langauge processing operations on Khmer language
Author-email: Vitou Phy <phy_vitou@live.com>
Project-URL: Homepage, https://github.com/vitouphy/khmer-nlp
Project-URL: Bug Tracker, https://github.com/vitouphy/khmer-nlp/issues
Classifier: Programming Language :: Python :: 3
Classifier: License :: OSI Approved :: MIT License
Classifier: Operating System :: OS Independent
Requires-Python: >=3.6
License-File: LICENSE
